reinit/__init__.py
reinit/app.py
reinit/git_ops.py
reinit-0.0.2.dist-info/LICENSE
reinit-0.0.2.dist-info/METADATA
reinit-0.0.2.dist-info/WHEEL
reinit-0.0.2.dist-info/entry_points.txt
reinit-0.0.2.dist-info/top_level.txt
reinit-0.0.2.dist-info/RECORD
