Metadata-Version: 2.1
Name: reinit
Version: 0.0.2
Summary: To re-initialize and push any github repository to your own github.
Home-page: https://github.com/zapp-oz/AutoGit
Author: Shresth Dewan
Author-email: shresthdewan@gmail.com
License: UNKNOWN
Platform: UNKNOWN
Classifier: Programming Language :: Python :: 3
Classifier: License :: OSI Approved :: MIT License
Classifier: Operating System :: OS Independent
Requires-Python: >=3.6
Requires-Dist: pygit2 (==1.3.0)
Requires-Dist: requests (==2.24.0)
